[
  {
    "id": "l1",
    "name": "Amina Khatoon",
    "image": "https://cdn.law.asia/wp-content/uploads/2022/01/Amina-Khatoon-1.png, M&A, taxation, energy",
    "experience": "23 Years",
    "licenseNumber": "LIC-AM001",
    "fee": "5000 BDT/hour",
    "availability": [
      "Monday",
      "Wednesday",
      "Friday"
    ],
    "contact": "+8801711027377"
  },
  {
    "id": "l2",
    "name": "Saqeb Mahbub",
    "image": "https://cdn.law.asia/wp-content/uploads/2022/01/Saqeb-Mahbub-1.png",
    "speciality": "Arbitration & ADR, corporate, labour & employment",
    "experience": "11 Years",
    "licenseNumber": "LIC-SA002",
    "fee": "5200 BDT/hour",
    "availability": [
      "Tuesday",
      "Thursday",
      "Saturday"
    ],
    "contact": "+8801725150912"
  },
  {
    "id": "l3",
    "name": "Shahdeen Malik",
    "image": "https://law.asia/wp-content/uploads/2022/01/Shahdeen-Malik.png",
    "speciality": "Corporate & banking, anti\u2011corruption, family law",
    "experience": "20 Years",
    "licenseNumber": "LIC-SH003",
    "fee": "5400 BDT/hour",
    "availability": [
      "Monday",
      "Tuesday",
      "Thursday"
    ],
    "contact": "+880247124915"
  },
  {
    "id": "l4",
    "name": "ABM Hamidul Mishbah",
    "image": "https://cdn.law.asia/wp-content/uploads/2022/01/Hamidul-Mishbah-1.png",
    "speciality": "IP, tech, telecom, competition, media",
    "experience": "19 Years",
    "licenseNumber": "LIC-AB004",
    "fee": "5600 BDT/hour",
    "availability": [
      "Wednesday",
      "Friday",
      "Sunday"
    ],
    "contact": "+8801911482175"
  },
  {
    "id": "l5",
    "name": "Khan Khalid Adnan",
    "image": "https://cdn.law.asia/wp-content/uploads/2022/01/Khan-Khalid-Adnan.png",
    "speciality": "Arbitration, banking & finance, corporate",
    "experience": "12 Years",
    "licenseNumber": "LIC-KH005",
    "fee": "5800 BDT/hour",
    "availability": [
      "Monday",
      "Wednesday",
      "Friday"
    ],
    "contact": "+8801730481628"
  },
  {
    "id": "l6",
    "name": "Shamsud Doulah",
    "image": "https://cdn.law.asia/wp-content/uploads/2022/01/Shamsud-Doulah-1.png",
    "speciality": "Corporate & commercial, litigation, IP enforcement",
    "experience": "30 Years",
    "licenseNumber": "LIC-SH006",
    "fee": "5000 BDT/hour",
    "availability": [
      "Tuesday",
      "Thursday",
      "Saturday"
    ],
    "contact": "+8801713382999"
  },
  {
    "id": "l7",
    "name": "Wahid Sadiq Khan",
    "image": "https://cdn.law.asia/wp-content/uploads/2022/01/Wahid-Sadiq-Khan-1.png",
    "speciality": "Labour & employment; corporate; white\u2011collar crime",
    "experience": "14 Years",
    "licenseNumber": "LIC-WA007",
    "fee": "5200 BDT/hour",
    "availability": [
      "Monday",
      "Tuesday",
      "Thursday"
    ],
    "contact": "+8801768054385"
  },
  {
    "id": "l8",
    "name": "Yousuf Ali",
    "image": "https://cdn.law.asia/wp-content/uploads/2022/01/Yousuf-Ali-1.png",
    "speciality": "Corporate; arbitration; tax; litigation; admiralty",
    "experience": "15 Years",
    "licenseNumber": "LIC-YO008",
    "fee": "5400 BDT/hour",
    "availability": [
      "Wednesday",
      "Friday",
      "Sunday"
    ],
    "contact": "+8801711595261"
  },
  {
    "id": "l9",
    "name": "Mydul Haque Khan",
    "image": "https://cdn.law.asia/wp-content/uploads/2022/01/Mydul-Haque-Khan-1.png",
    "speciality": "Banking & finance; corporate & commercial",
    "experience": "15 Years",
    "licenseNumber": "LIC-MY009",
    "fee": "5600 BDT/hour",
    "availability": [
      "Monday",
      "Wednesday",
      "Friday"
    ],
    "contact": "+8801711027377"
  },
  {
    "id": "l10",
    "name": "Imtiaz Uddin Ahmad Asif",
    "image": "https://cdn.law.asia/wp-content/uploads/2022/01/Imtiaz-Ahmad-Asif-1.png",
    "speciality": "Corporate & commercial; M&A; project finance",
    "experience": "22 Years",
    "licenseNumber": "LIC-IM010",
    "fee": "5800 BDT/hour",
    "availability": [
      "Tuesday",
      "Thursday",
      "Saturday"
    ],
    "contact": "+8801725150912"
  }
  
]